README.rst
setup.py
django_wordpress_auth_lite.egg-info/PKG-INFO
django_wordpress_auth_lite.egg-info/SOURCES.txt
django_wordpress_auth_lite.egg-info/dependency_links.txt
django_wordpress_auth_lite.egg-info/requires.txt
django_wordpress_auth_lite.egg-info/top_level.txt
wordpress_auth_lite/__init__.py
wordpress_auth_lite/decorators.py
wordpress_auth_lite/middleware.py
wordpress_auth_lite/models.py
wordpress_auth_lite/utils.py
wordpress_auth_lite/views.py