Metadata-Version: 1.1
Name: django-wordpress-auth-lite
Version: 0.1.0
Summary: Django integration with WordPress authentication and WITHOUT roles / capabilities system.
Home-page: https://github.com/ScilCoop/django-wordpress-auth-lite.git
Author: UNKNOWN
Author-email: UNKNOWN
License: UNKNOWN
Platform: UNKNOWN
Classifier: Environment :: Web Environment
Classifier: Framework :: Django
Classifier: Intended Audience :: Developers
Classifier: Programming Language :: Python :: 2.7
Classifier: Programming Language :: Python :: 3
Classifier: Programming Language :: Python :: 3.3
Classifier: Topic :: Software Development :: Libraries :: Python Modules
Classifier: Topic :: Utilities
